{
  "version": 1,
  "author": "Uri Shaked",
  "editor": "wokwi",
  "parts": [
    { "type": "wokwi-arduino-uno", "id": "uno", "top": 120, "left": 20, "attrs": {} },
    {
      "type": "wokwi-resistor",
      "id": "r1",
      "top": 67,
      "left": 115,
      "rotate": 90,
      "attrs": { "value": "220" }
    },
    {
      "type": "wokwi-led",
      "id": "led",
      "top": -20.4,
      "left": 93,
      "rotate": 90,
      "attrs": { "color": "red" }
    },
    {
      "type": "wokwi-resistor",
      "id": "r2",
      "top": 52.8,
      "left": 181.85,
      "rotate": 90,
      "attrs": { "value": "1000" }
    },
    {
      "type": "wokwi-led",
      "id": "led1",
      "top": -58.8,
      "left": 93,
      "rotate": 90,
      "attrs": { "color": "green" }
    },
    {
      "type": "wokwi-led",
      "id": "led2",
      "top": -39.6,
      "left": 93,
      "rotate": 90,
      "attrs": { "color": "yellow" }
    },
    {
      "type": "wokwi-resistor",
      "id": "r3",
      "top": 52.8,
      "left": 153.05,
      "rotate": 90,
      "attrs": { "value": "1000" }
    }
  ],
  "connections": [
    [ "uno:GND.1", "led:C", "black", [] ],
    [ "r1:1", "led:A", "blue", [] ],
    [ "uno:13", "r1:2", "blue", [] ],
    [ "uno:8", "r2:2", "green", [ "h-1", "v-41.4" ] ],
    [ "r2:1", "led1:A", "green", [ "h0" ] ],
    [ "led1:C", "uno:GND.1", "black", [ "v0" ] ],
    [ "r3:1", "led2:A", "green", [ "h0" ] ],
    [ "r3:2", "uno:9", "green", [ "h0" ] ],
    [ "led2:C", "uno:GND.1", "black", [ "v105.6", "h-38" ] ]
  ],
  "dependencies": {}
}
